[
  {
    "id": 339958,
    "slug": "persona-5-royal",
    "name": "Persona 5 Royal",
    "name_original": "Persona 5 Royal",
    "description": "Wear the mask.  Reveal your truth. Prepare for an all-new RPG experience in Persona®5 Royal based in the universe of the award-winning series, Persona®! Don the mask of Joker and join the Phantom Thieves of Hearts. Break free from the chains of modern society and stage grand heists to infiltrate the minds of the corrupt and make them change their ways! Persona®5 Royal is packed with new characters, story depth, new locations to explore, a new grappling hook mechanic for access to new areas. With a new semester at Shujin Academy, get ready to strengthen your abilities in the metaverse and in your daily life. Persona®5 Royal presents a unique visual style and award nominated composer Shoji Meguro returns with an all-new soundtrack. Explore Tokyo, unlock new Personas, customize your own personal Thieves Den, discover a never-before-seen story arc, cutscenes, alternate endings, and more!",
    "metacritic": 94,
    "metacritic_platforms": [
      {
        "metascore": 94,
        "url": "https://www.metacritic.com/game/xbox-series-x/persona-5-royal",
        "platform": {
          "platform": 186,
          "name": "Xbox Series S/X",
          "slug": "xbox-series-x"
        }
      },
      {
        "metascore": 94,
        "url": "https://www.metacritic.com/game/switch/persona-5-royal",
        "platform": {
          "platform": 7,
          "name": "Nintendo Switch",
          "slug": "nintendo-switch"
        }
      },
      {
        "metascore": 91,
        "url": "https://www.metacritic.com/game/playstation-5/persona-5-royal",
        "platform": {
          "platform": 187,
          "name": "PlayStation 5",
          "slug": "playstation5"
        }
      },
      {
        "metascore": 95,
        "url": "https://www.metacritic.com/game/pc/persona-5-royal",
        "platform": {
          "platform": 4,
          "name": "PC",
          "slug": "pc"
        }
      },
      {
        "metascore": 95,
        "url": "https://www.metacritic.com/game/playstation-4/persona-5-royal",
        "platform": {
          "platform": 18,
          "name": "PlayStation 4",
          "slug": "playstation4"
        }
      }
    ],
    "released": "2020-03-31",
    "tba": false,
    "updated": "2025-04-27T19:10:33",
    "background_image": "https://media.rawg.io/media/games/a9c/a9c789951de65da545d51f664b4f2ce0.jpg",
    "background_image_additional": "https://media.rawg.io/media/screenshots/b26/b2604ecc559bccfb72dca2c869f53b63.jpg",
    "website": "https://atlus.com/p5r/",
    "rating": 4.76,
    "rating_top": 5,
    "ratings": [
      {
        "id": 5,
        "title": "exceptional",
        "count": 424,
        "percent": 83.63
      },
      {
        "id": 4,
        "title": "recommended",
        "count": 58,
        "percent": 11.44
      },
      {
        "id": 3,
        "title": "meh",
        "count": 17,
        "percent": 3.35
      },
      {
        "id": 1,
        "title": "skip",
        "count": 8,
        "percent": 1.58
      }
    ],
    "reactions": {
      "1": 3,
      "2": 3,
      "3": 6,
      "4": 1,
      "7": 3,
      "10": 2,
      "11": 1,
      "12": 4
    },
    "added": 3068,
    "added_by_status": {
      "yet": 225,
      "owned": 1671,
      "beaten": 448,
      "toplay": 482,
      "dropped": 83,
      "playing": 159
    },
    "playtime": 13,
    "screenshots_count": 6,
    "movies_count": 0,
    "creators_count": 9,
    "achievements_count": 343,
    "parent_achievements_count": 129,
    "reddit_url": "https://www.reddit.com/r/Persona5/",
    "reddit_name": "",
    "reddit_description": "",
    "reddit_logo": "",
    "reddit_count": 5150,
    "twitch_count": 0,
    "youtube_count": 1000000,
    "reviews_text_count": 10,
    "ratings_count": 497,
    "suggestions_count": 329,
    "alternative_names": [
      "ペルソナ5 ザ・ロイヤル",
      "女神异闻录5皇家版"
    ],
    "metacritic_url": "https://www.metacritic.com/game/playstation-4/persona-5-royal",
    "parents_count": 1,
    "additions_count": 0,
    "game_series_count": 0,
    "user_game": null,
    "reviews_count": 507,
    "saturated_color": "0f0f0f",
    "dominant_color": "0f0f0f",
    "parent_platforms": [
      {
        "platform": {
          "id": 1,
          "name": "PC",
          "slug": "pc"
        }
      },
      {
        "platform": {
          "id": 2,
          "name": "PlayStation",
          "slug": "playstation"
        }
      },
      {
        "platform": {
          "id": 3,
          "name": "Xbox",
          "slug": "xbox"
        }
      },
      {
        "platform": {
          "id": 7,
          "name": "Nintendo",
          "slug": "nintendo"
        }
      }
    ],
    "platforms": [
      {
        "platform": {
          "id": 186,
          "name": "Xbox Series S/X",
          "slug": "xbox-series-x",
          "image": null,
          "year_end": null,
          "year_start": 2020,
          "games_count": 1079,
          "image_background": "https://media.rawg.io/media/games/618/618c2031a07bbff6b4f611f10b6bcdbc.jpg"
        },
        "released_at": "2020-03-31",
        "requirements": {}
      },
      {
        "platform": {
          "id": 4,
          "name": "PC",
          "slug": "pc",
          "image": null,
          "year_end": null,
          "year_start": null,
          "games_count": 547964,
          "image_background": "https://media.rawg.io/media/games/511/5118aff5091cb3efec399c808f8c598f.jpg"
        },
        "released_at": "2020-03-31",
        "requirements": {
          "minimum": "Minimum:\nRequires a 64-bit processor and operating system\nOS: Windows 10\nProcessor: Intel Core i7-4790, 3.4 GHz | AMD Ryzen 5 1500X, 3.5 GHz\nMemory: 8 GB RAM\nGraphics: Nvidia GeForce GTX 650 Ti, 2 GB | AMD Radeon R7 360, 2 GB\nDirectX: Version 11\nStorage: 41 GB available space\nAdditional Notes: Low 720p @ 60 FPS. Requires a CPU which supports the AVX and SSE4.2 instruction set.",
          "recommended": "Recommended:\nRequires a 64-bit processor and operating system\nOS: Windows 10\nProcessor: Intel Core i7-4790, 3.4 GHz | AMD Ryzen 5 1500X 3.5 Ghz\nMemory: 8 GB RAM\nGraphics: Nvidia GeForce GTX 760, 2 GB | AMD Radeon HD 7870, 2 GB\nDirectX: Version 11\nStorage: 41 GB available space\nAdditional Notes: High 1080p @ 60 FPS"
        }
      },
      {
        "platform": {
          "id": 187,
          "name": "PlayStation 5",
          "slug": "playstation5",
          "image": null,
          "year_end": null,
          "year_start": 2020,
          "games_count": 1244,
          "image_background": "https://media.rawg.io/media/games/34b/34b1f1850a1c06fd971bc6ab3ac0ce0e.jpg"
        },
        "released_at": "2020-03-31",
        "requirements": {}
      },
      {
        "platform": {
          "id": 7,
          "name": "Nintendo Switch",
          "slug": "nintendo-switch",
          "image": null,
          "year_end": null,
          "year_start": null,
          "games_count": 5626,
          "image_background": "https://media.rawg.io/media/games/849/849414b978db37d4563ff9e4b0d3a787.jpg"
        },
        "released_at": "2020-03-31",
        "requirements": {}
      },
      {
        "platform": {
          "id": 1,
          "name": "Xbox One",
          "slug": "xbox-one",
          "image": null,
          "year_end": null,
          "year_start": null,
          "games_count": 5696,
          "image_background": "https://media.rawg.io/media/games/021/021c4e21a1824d2526f925eff6324653.jpg"
        },
        "released_at": "2020-03-31",
        "requirements": {}
      },
      {
        "platform": {
          "id": 18,
          "name": "PlayStation 4",
          "slug": "playstation4",
          "image": null,
          "year_end": null,
          "year_start": null,
          "games_count": 6919,
          "image_background": "https://media.rawg.io/media/games/d1a/d1a2e99ade53494c6330a0ed945fe823.jpg"
        },
        "released_at": "2020-03-31",
        "requirements": {}
      }
    ],
    "stores": [
      {
        "id": 858685,
        "url": "",
        "store": {
          "id": 6,
          "name": "Nintendo Store",
          "slug": "nintendo",
          "domain": "nintendo.com",
          "games_count": 9129,
          "image_background": "https://media.rawg.io/media/games/8cc/8cce7c0e99dcc43d66c8efd42f9d03e3.jpg"
        }
      },
      {
        "id": 858684,
        "url": "",
        "store": {
          "id": 1,
          "name": "Steam",
          "slug": "steam",
          "domain": "store.steampowered.com",
          "games_count": 110950,
          "image_background": "https://media.rawg.io/media/games/120/1201a40e4364557b124392ee50317b99.jpg"
        }
      },
      {
        "id": 385794,
        "url": "",
        "store": {
          "id": 3,
          "name": "PlayStation Store",
          "slug": "playstation-store",
          "domain": "store.playstation.com",
          "games_count": 8040,
          "image_background": "https://media.rawg.io/media/games/587/587588c64afbff80e6f444eb2e46f9da.jpg"
        }
      }
    ],
    "developers": [
      {
        "id": 13953,
        "name": "Atlus",
        "slug": "atlus",
        "games_count": 114,
        "image_background": "https://media.rawg.io/media/games/68a/68a5aaddf51fa089fe1d2fcc9aa1b62b.jpg"
      }
    ],
    "genres": [
      {
        "id": 3,
        "name": "Adventure",
        "slug": "adventure",
        "games_count": 146789,
        "image_background": "https://media.rawg.io/media/games/942/9424d6bb763dc38d9378b488603c87fa.jpg"
      },
      {
        "id": 5,
        "name": "RPG",
        "slug": "role-playing-games-rpg",
        "games_count": 59505,
        "image_background": "https://media.rawg.io/media/games/a6c/a6ccd34125c594abf1a9c9821b9a715d.jpg"
      }
    ],
    "tags": [
      {
        "id": 31,
        "name": "Singleplayer",
        "slug": "singleplayer",
        "language": "eng",
        "games_count": 239144,
        "image_background": "https://media.rawg.io/media/games/73e/73eecb8909e0c39fb246f457b5d6cbbe.jpg"
      },
      {
        "id": 40847,
        "name": "Steam Achievements",
        "slug": "steam-achievements",
        "language": "eng",
        "games_count": 45430,
        "image_background": "https://media.rawg.io/media/games/20a/20aa03a10cda45239fe22d035c0ebe64.jpg"
      },
      {
        "id": 40836,
        "name": "Full controller support",
        "slug": "full-controller-support",
        "language": "eng",
        "games_count": 21419,
        "image_background": "https://media.rawg.io/media/games/4be/4be6a6ad0364751a96229c56bf69be59.jpg"
      },
      {
        "id": 40849,
        "name": "Steam Cloud",
        "slug": "steam-cloud",
        "language": "eng",
        "games_count": 22047,
        "image_background": "https://media.rawg.io/media/games/e6d/e6de699bd788497f4b52e2f41f9698f2.jpg"
      },
      {
        "id": 42,
        "name": "Great Soundtrack",
        "slug": "great-soundtrack",
        "language": "eng",
        "games_count": 3426,
        "image_background": "https://media.rawg.io/media/games/198/1988a337305e008b41d7f536ce9b73f6.jpg"
      },
      {
        "id": 24,
        "name": "RPG",
        "slug": "rpg",
        "language": "eng",
        "games_count": 24245,
        "image_background": "https://media.rawg.io/media/games/618/618c2031a07bbff6b4f611f10b6bcdbc.jpg"
      },
      {
        "id": 118,
        "name": "Story Rich",
        "slug": "story-rich",
        "language": "eng",
        "games_count": 24813,
        "image_background": "https://media.rawg.io/media/games/6cd/6cd653e0aaef5ff8bbd295bf4bcb12eb.jpg"
      },
      {
        "id": 34,
        "name": "Violent",
        "slug": "violent",
        "language": "eng",
        "games_count": 7301,
        "image_background": "https://media.rawg.io/media/games/0af/0af85e8edddfa55368e47c539914a220.jpg"
      },
      {
        "id": 134,
        "name": "Anime",
        "slug": "anime",
        "language": "eng",
        "games_count": 15437,
        "image_background": "https://media.rawg.io/media/games/bee/bee483efadcf9d7e657e52184316a34e.jpg"
      },
      {
        "id": 165,
        "name": "Colorful",
        "slug": "colorful",
        "language": "eng",
        "games_count": 25983,
        "image_background": "https://media.rawg.io/media/screenshots/d07/d07a7e2f7be2428c51ad26326c84e21d.jpg"
      },
      {
        "id": 101,
        "name": "Turn-Based Strategy",
        "slug": "turn-based-strategy",
        "language": "eng",
        "games_count": 5995,
        "image_background": "https://media.rawg.io/media/games/238/2383a172b4d50a7b44e07980eb7141ea.jpg"
      },
      {
        "id": 50,
        "name": "Sexual Content",
        "slug": "sexual-content",
        "language": "eng",
        "games_count": 7609,
        "image_background": "https://media.rawg.io/media/games/370/3703c683968a54f09630dcf03366ea35.jpg"
      },
      {
        "id": 218,
        "name": "Multiple Endings",
        "slug": "multiple-endings",
        "language": "eng",
        "games_count": 10354,
        "image_background": "https://media.rawg.io/media/games/4cf/4cfc6b7f1850590a4634b08bfab308ab.jpg"
      },
      {
        "id": 40937,
        "name": "Steam Trading Cards",
        "slug": "steam-trading-cards-2",
        "language": "eng",
        "games_count": 750,
        "image_background": "https://media.rawg.io/media/games/260/26023c855f1769a93411d6a7ea084632.jpeg"
      },
      {
        "id": 90,
        "name": "Visual Novel",
        "slug": "visual-novel",
        "language": "eng",
        "games_count": 8560,
        "image_background": "https://media.rawg.io/media/games/8d6/8d69eb6c32ed6acfd75f82d532144993.jpg"
      },
      {
        "id": 233,
        "name": "JRPG",
        "slug": "jrpg",
        "language": "eng",
        "games_count": 4835,
        "image_background": "https://media.rawg.io/media/games/b2c/b2c9c6115114c8f7d461b5430e8a7d4a.jpg"
      },
      {
        "id": 142,
        "name": "Detective",
        "slug": "detective",
        "language": "eng",
        "games_count": 3737,
        "image_background": "https://media.rawg.io/media/games/b2c/b2c9c6115114c8f7d461b5430e8a7d4a.jpg"
      },
      {
        "id": 175,
        "name": "Turn-Based Combat",
        "slug": "turn-based-combat",
        "language": "eng",
        "games_count": 5744,
        "image_background": "https://media.rawg.io/media/games/75c/75c086892cbf0aed952293f440a935a4.jpg"
      },
      {
        "id": 216,
        "name": "Heist",
        "slug": "heist",
        "language": "eng",
        "games_count": 570,
        "image_background": "https://media.rawg.io/media/games/b50/b501727147644474562935f19a60134e.jpg"
      },
      {
        "id": 572,
        "name": "Emotional",
        "slug": "emotional",
        "language": "eng",
        "games_count": 3792,
        "image_background": "https://media.rawg.io/media/games/7ad/7adc6352280fe0e6626902e444e22195.jpg"
      },
      {
        "id": 160,
        "name": "Dating Sim",
        "slug": "dating-sim",
        "language": "eng",
        "games_count": 6191,
        "image_background": "https://media.rawg.io/media/screenshots/5d9/5d9d6da555c357edde9cfa2db622083f.jpg"
      },
      {
        "id": 206,
        "name": "Party-Based RPG",
        "slug": "party-based-rpg",
        "language": "eng",
        "games_count": 1358,
        "image_background": "https://media.rawg.io/media/games/d89/d89bd0cf4fcdc10820892980cbba0f49.jpg"
      },
      {
        "id": 295,
        "name": "Soundtrack",
        "slug": "soundtrack",
        "language": "eng",
        "games_count": 3199,
        "image_background": "https://media.rawg.io/media/games/dec/decdfa154a72265cd2914097666a99d5.jpg"
      }
    ],
    "publishers": [
      {
        "id": 3408,
        "name": "SEGA",
        "slug": "sega-2",
        "games_count": 1263,
        "image_background": "https://media.rawg.io/media/games/0fd/0fd84d36596a83ef2e5a35f63a072218.jpg"
      },
      {
        "id": 9065,
        "name": "Atlus",
        "slug": "atlus",
        "games_count": 247,
        "image_background": "https://media.rawg.io/media/games/9d3/9d3e5f3b9fbe3769e693c93b5b91300a.jpg"
      }
    ],
    "esrb_rating": {
      "id": 4,
      "name": "Mature",
      "slug": "mature"
    },
    "clip": null,
    "description_raw": "Wear the mask.  Reveal your truth. Prepare for an all-new RPG experience in Persona®5 Royal based in the universe of the award-winning series, Persona®! Don the mask of Joker and join the Phantom Thieves of Hearts. Break free from the chains of modern society and stage grand heists to infiltrate the minds of the corrupt and make them change their ways! Persona®5 Royal is packed with new characters, story depth, new locations to explore, a new grappling hook mechanic for access to new areas. With a new semester at Shujin Academy, get ready to strengthen your abilities in the metaverse and in your daily life. Persona®5 Royal presents a unique visual style and award nominated composer Shoji Meguro returns with an all-new soundtrack. Explore Tokyo, unlock new Personas, customize your own personal Thieves Den, discover a never-before-seen story arc, cutscenes, alternate endings, and more!"
  },
  {
    "id": 974379,
    "slug": "dragon-ball-sparking-zero",
    "name": "DRAGON BALL: Sparking! ZERO",
    "name_original": "DRAGON BALL: Sparking! ZERO",
    "description": "DRAGON BALL: Sparking! ZERO takes the legendary gameplay of the Budokai Tenkaichi series and raises it to whole new levels. DRAGON BALL: Sparking! ZERO has an incredible number of playable characters, each with signature abilities, transformations and techniques. Unleash the fighting spirit within you and take the fight to arenas that crumble and react to your power as the battle rages on.",
    "metacritic": null,
    "metacritic_platforms": [],
    "released": null,
    "tba": true,
    "updated": "2025-04-19T20:41:41",
    "background_image": "https://media.rawg.io/media/screenshots/64f/64fdee7e7b863fbc22460cb8e38614b9.jpg",
    "background_image_additional": "https://media.rawg.io/media/screenshots/2a2/2a208aaa3169f7efa0be514cde5557f5.jpg",
    "website": "https://dragonballsparkingzero.com/",
    "rating": 4.86,
    "rating_top": 5,
    "ratings": [
      {
        "id": 5,
        "title": "exceptional",
        "count": 6,
        "percent": 85.71
      },
      {
        "id": 4,
        "title": "recommended",
        "count": 1,
        "percent": 14.29
      }
    ],
    "reactions": null,
    "added": 107,
    "added_by_status": {
      "yet": 9,
      "owned": 55,
      "beaten": 7,
      "toplay": 22,
      "dropped": 5,
      "playing": 9
    },
    "playtime": 13,
    "screenshots_count": 6,
    "movies_count": 0,
    "creators_count": 0,
    "achievements_count": 29,
    "parent_achievements_count": 29,
    "reddit_url": "",
    "reddit_name": "",
    "reddit_description": "",
    "reddit_logo": "",
    "reddit_count": 0,
    "twitch_count": 0,
    "youtube_count": 0,
    "reviews_text_count": 0,
    "ratings_count": 7,
    "suggestions_count": 202,
    "alternative_names": [],
    "metacritic_url": "https://www.metacritic.com/game/dragon-ball-sparking-zero/",
    "parents_count": 0,
    "additions_count": 0,
    "game_series_count": 56,
    "user_game": null,
    "reviews_count": 7,
    "saturated_color": "0f0f0f",
    "dominant_color": "0f0f0f",
    "parent_platforms": [
      {
        "platform": {
          "id": 1,
          "name": "PC",
          "slug": "pc"
        }
      },
      {
        "platform": {
          "id": 2,
          "name": "PlayStation",
          "slug": "playstation"
        }
      },
      {
        "platform": {
          "id": 3,
          "name": "Xbox",
          "slug": "xbox"
        }
      }
    ],
    "platforms": [
      {
        "platform": {
          "id": 4,
          "name": "PC",
          "slug": "pc",
          "image": null,
          "year_end": null,
          "year_start": null,
          "games_count": 547583,
          "image_background": "https://media.rawg.io/media/games/fc1/fc1307a2774506b5bd65d7e8424664a7.jpg"
        },
        "released_at": null,
        "requirements": {
          "minimum": "Minimum:\nRequires a 64-bit processor and operating system\nOS: Windows 10\nProcessor: Intel Core i5-9600K / AMD Ryzen 5 2600\nMemory: 8 GB RAM\nGraphics: Nvidia GeForce GTX 980 / AMD Radeon RX 590 / Intel Arc A750\nDirectX: Version 12\nStorage: 29 GB available space\nAdditional Notes: Estimated performance: 1080p/60fps with graphics settings at &quot;Low&quot;. Framerate might drop in graphics-intensive scenes. - 64-bit processor and operating system are required.",
          "recommended": "Recommended:\nRequires a 64-bit processor and operating system\nOS: Windows 10 / Windows 11\nProcessor: Intel Core i7-9700K / AMD Ryzen 5 3600\nMemory: 16 GB RAM\nGraphics: Nvidia GeForce RTX 2060 / AMD Radeon RX Vega 64\nDirectX: Version 12\nStorage: 29 GB available space\nAdditional Notes: Estimated performance: 1080p/60fps with graphics settings at &quot;High&quot;. Framerate might drop in graphics-intensive scenes. - 64-bit processor and operating system are required. - Windows 10 (Version 1809 or later) and a 4GB VRAM GPU (graphics board or video card) are required for DirectX 12 API."
        }
      },
      {
        "platform": {
          "id": 187,
          "name": "PlayStation 5",
          "slug": "playstation5",
          "image": null,
          "year_end": null,
          "year_start": 2020,
          "games_count": 1241,
          "image_background": "https://media.rawg.io/media/games/9f1/9f1891779cb20f44de93cef33b067e50.jpg"
        },
        "released_at": null,
        "requirements": {}
      },
      {
        "platform": {
          "id": 186,
          "name": "Xbox Series S/X",
          "slug": "xbox-series-x",
          "image": null,
          "year_end": null,
          "year_start": 2020,
          "games_count": 1075,
          "image_background": "https://media.rawg.io/media/games/6cc/6cc23249972a427f697a3d10eb57a820.jpg"
        },
        "released_at": null,
        "requirements": {}
      }
    ],
    "stores": [
      {
        "id": 991207,
        "url": "",
        "store": {
          "id": 1,
          "name": "Steam",
          "slug": "steam",
          "domain": "store.steampowered.com",
          "games_count": 110568,
          "image_background": "https://media.rawg.io/media/games/942/9424d6bb763dc38d9378b488603c87fa.jpg"
        }
      }
    ],
    "developers": [
      {
        "id": 19710,
        "name": "Spike Chunsoft",
        "slug": "spike-chunsoft",
        "games_count": 56,
        "image_background": "https://media.rawg.io/media/games/201/201012468d5d20ff06cca1007815d0e4.jpg"
      }
    ],
    "genres": [
      {
        "id": 4,
        "name": "Action",
        "slug": "action",
        "games_count": 186751,
        "image_background": "https://media.rawg.io/media/games/4be/4be6a6ad0364751a96229c56bf69be59.jpg"
      },
      {
        "id": 6,
        "name": "Fighting",
        "slug": "fighting",
        "games_count": 11763,
        "image_background": "https://media.rawg.io/media/games/35b/35b47c4d85cd6e08f3e2ca43ea5ce7bb.jpg"
      }
    ],
    "tags": [
      {
        "id": 31,
        "name": "Singleplayer",
        "slug": "singleplayer",
        "language": "eng",
        "games_count": 238777,
        "image_background": "https://media.rawg.io/media/games/8cc/8cce7c0e99dcc43d66c8efd42f9d03e3.jpg"
      },
      {
        "id": 40847,
        "name": "Steam Achievements",
        "slug": "steam-achievements",
        "language": "eng",
        "games_count": 45242,
        "image_background": "https://media.rawg.io/media/games/198/1988a337305e008b41d7f536ce9b73f6.jpg"
      },
      {
        "id": 7,
        "name": "Multiplayer",
        "slug": "multiplayer",
        "language": "eng",
        "games_count": 40575,
        "image_background": "https://media.rawg.io/media/games/b8c/b8c243eaa0fbac8115e0cdccac3f91dc.jpg"
      },
      {
        "id": 40836,
        "name": "Full controller support",
        "slug": "full-controller-support",
        "language": "eng",
        "games_count": 21335,
        "image_background": "https://media.rawg.io/media/games/34b/34b1f1850a1c06fd971bc6ab3ac0ce0e.jpg"
      },
      {
        "id": 40849,
        "name": "Steam Cloud",
        "slug": "steam-cloud",
        "language": "eng",
        "games_count": 21933,
        "image_background": "https://media.rawg.io/media/games/be0/be01c3d7d8795a45615da139322ca080.jpg"
      },
      {
        "id": 18,
        "name": "Co-op",
        "slug": "co-op",
        "language": "eng",
        "games_count": 13165,
        "image_background": "https://media.rawg.io/media/games/2ba/2bac0e87cf45e5b508f227d281c9252a.jpg"
      },
      {
        "id": 36,
        "name": "Open World",
        "slug": "open-world",
        "language": "eng",
        "games_count": 8508,
        "image_background": "https://media.rawg.io/media/games/d82/d82990b9c67ba0d2d09d4e6fa88885a7.jpg"
      },
      {
        "id": 411,
        "name": "cooperative",
        "slug": "cooperative",
        "language": "eng",
        "games_count": 5889,
        "image_background": "https://media.rawg.io/media/games/20a/20aa03a10cda45239fe22d035c0ebe64.jpg"
      },
      {
        "id": 149,
        "name": "Third Person",
        "slug": "third-person",
        "language": "eng",
        "games_count": 13305,
        "image_background": "https://media.rawg.io/media/games/5c0/5c0dd63002cb23f804aab327d40ef119.jpg"
      },
      {
        "id": 198,
        "name": "Split Screen",
        "slug": "split-screen",
        "language": "eng",
        "games_count": 7474,
        "image_background": "https://media.rawg.io/media/games/f95/f95ec06eddda5c5bf206618c49cd3e68.jpg"
      },
      {
        "id": 69,
        "name": "Action-Adventure",
        "slug": "action-adventure",
        "language": "eng",
        "games_count": 19060,
        "image_background": "https://media.rawg.io/media/games/af7/af7a831001c5c32c46e950cc883b8cb7.jpg"
      },
      {
        "id": 72,
        "name": "Local Multiplayer",
        "slug": "local-multiplayer",
        "language": "eng",
        "games_count": 13650,
        "image_background": "https://media.rawg.io/media/games/e0f/e0f05a97ff926acf4c8f43e0849b6832.jpg"
      },
      {
        "id": 157,
        "name": "PvP",
        "slug": "pvp",
        "language": "eng",
        "games_count": 10864,
        "image_background": "https://media.rawg.io/media/games/cc7/cc77035eb972f179f5090ee2a0fabd99.jpg"
      },
      {
        "id": 134,
        "name": "Anime",
        "slug": "anime",
        "language": "eng",
        "games_count": 15394,
        "image_background": "https://media.rawg.io/media/games/c40/c40f9f0a3d1b4601a7a44d230c95f126.jpg"
      },
      {
        "id": 571,
        "name": "3D",
        "slug": "3d",
        "language": "eng",
        "games_count": 89206,
        "image_background": "https://media.rawg.io/media/games/c89/c89ca70716080733d03724277df2c6c7.jpg"
      },
      {
        "id": 114,
        "name": "Physics",
        "slug": "physics",
        "language": "eng",
        "games_count": 20543,
        "image_background": "https://media.rawg.io/media/screenshots/69b/69bb243ea9896ddfc2e051b58e81624d.jpg"
      },
      {
        "id": 1465,
        "name": "combat",
        "slug": "combat",
        "language": "eng",
        "games_count": 14472,
        "image_background": "https://media.rawg.io/media/games/e1f/e1ffbeb1bac25b19749ad285ca29e158.jpg"
      },
      {
        "id": 170,
        "name": "Competitive",
        "slug": "competitive",
        "language": "eng",
        "games_count": 1234,
        "image_background": "https://media.rawg.io/media/games/1a1/1a17e9b6286edb7e1f1e510110ccb0c0.jpg"
      },
      {
        "id": 45878,
        "name": "Online PvP",
        "slug": "online-pvp",
        "language": "eng",
        "games_count": 5615,
        "image_background": "https://media.rawg.io/media/games/370/3703c683968a54f09630dcf03366ea35.jpg"
      },
      {
        "id": 171,
        "name": "PvE",
        "slug": "pve",
        "language": "eng",
        "games_count": 6623,
        "image_background": "https://media.rawg.io/media/screenshots/6d3/6d367773c06886535620f2d7fb1cb866.jpg"
      },
      {
        "id": 116,
        "name": "2.5D",
        "slug": "25d",
        "language": "eng",
        "games_count": 2529,
        "image_background": "https://media.rawg.io/media/games/8a0/8a02f84a5916ede2f923b88d5f8217ba.jpg"
      },
      {
        "id": 45201,
        "name": "Remote Play Together",
        "slug": "remote-play-together",
        "language": "eng",
        "games_count": 3511,
        "image_background": "https://media.rawg.io/media/games/a4c/a4c1fd4265ac2c1edc87cb9a6a7644e4.jpg"
      },
      {
        "id": 91686,
        "name": "Family Sharing",
        "slug": "family-sharing",
        "language": "eng",
        "games_count": 17912,
        "image_background": "https://media.rawg.io/media/games/10b/10bbea9e3307778dd9a4dce704aede2e.jpg"
      },
      {
        "id": 254,
        "name": "Spectacle fighter",
        "slug": "spectacle-fighter",
        "language": "eng",
        "games_count": 733,
        "image_background": "https://media.rawg.io/media/games/372/3724c266c9d028a6cff791dd8df4b98e.jpg"
      },
      {
        "id": 46114,
        "name": "Shared/Split Screen PvP",
        "slug": "sharedsplit-screen-pvp",
        "language": "eng",
        "games_count": 2562,
        "image_background": "https://media.rawg.io/media/games/dfe/dfe14d30ed6fccd9db4ae79d3be51d54.jpg"
      },
      {
        "id": 240,
        "name": "Martial Arts",
        "slug": "martial-arts",
        "language": "eng",
        "games_count": 628,
        "image_background": "https://media.rawg.io/media/games/75e/75e95dc8d5b290f6875062af6b35fb59.jpg"
      },
      {
        "id": 91537,
        "name": "HDR available",
        "slug": "hdr-available",
        "language": "eng",
        "games_count": 127,
        "image_background": "https://media.rawg.io/media/games/686/686909717c3aa01518bc42ae2bf4259e.jpg"
      },
      {
        "id": 49961,
        "name": "3D Fighter",
        "slug": "3d-fighter-2",
        "language": "eng",
        "games_count": 1139,
        "image_background": "https://media.rawg.io/media/screenshots/b0f/b0ff50755a27be1ad8b39908b1d2d366.jpg"
      },
      {
        "id": 56826,
        "name": "3D-файтинг",
        "slug": "3d-faiting",
        "language": "eng",
        "games_count": 1093,
        "image_background": "https://media.rawg.io/media/screenshots/544/544fbb0b70cff90a73b01d72bbd7185a.jpeg"
      }
    ],
    "publishers": [
      {
        "id": 8352,
        "name": "Bandai Namco Entertainment",
        "slug": "bandai-namco-entertainment",
        "games_count": 604,
        "image_background": "https://media.rawg.io/media/games/b92/b924c4beeed6617201d5d91511cfcf8e.jpg"
      }
    ],
    "esrb_rating": {
      "id": 3,
      "name": "Teen",
      "slug": "teen"
    },
    "clip": null,
    "description_raw": "DRAGON BALL: Sparking! ZERO takes the legendary gameplay of the Budokai Tenkaichi series and raises it to whole new levels. DRAGON BALL: Sparking! ZERO has an incredible number of playable characters, each with signature abilities, transformations and techniques. Unleash the fighting spirit within you and take the fight to arenas that crumble and react to your power as the battle rages on."
  },
  {
    "id": 58781,
    "slug": "the-elder-scrolls-vi",
    "name": "The Elder Scrolls VI",
    "name_original": "The Elder Scrolls VI",
    "description": "Currently in pre-production at Bethesda Game Studios, the acclaimed developers of Skyrim and Fallout 4. The highly-anticipated next chapter in the iconic The Elder Scrolls series.",
    "metacritic": null,
    "metacritic_platforms": [],
    "released": null,
    "tba": true,
    "updated": "2024-04-12T10:28:14",
    "background_image": "https://media.rawg.io/media/games/b40/b40eba32d8715d5fdf9634939fe0eca3.jpg",
    "background_image_additional": null,
    "website": "",
    "rating": 4.86,
    "rating_top": 5,
    "ratings": [
      {
        "id": 5,
        "title": "exceptional",
        "count": 6,
        "percent": 85.71
      },
      {
        "id": 4,
        "title": "recommended",
        "count": 1,
        "percent": 14.29
      }
    ],
    "reactions": {},
    "added": 236,
    "added_by_status": {
      "yet": 28,
      "owned": 19,
      "beaten": 1,
      "toplay": 187,
      "playing": 1
    },
    "playtime": 0,
    "screenshots_count": 1,
    "movies_count": 0,
    "creators_count": 1,
    "achievements_count": 0,
    "parent_achievements_count": 0,
    "reddit_url": "https://www.reddit.com/r/ElderScrolls/",
    "reddit_name": "",
    "reddit_description": "",
    "reddit_logo": "",
    "reddit_count": 9457,
    "twitch_count": 3,
    "youtube_count": 440700,
    "reviews_text_count": 1,
    "ratings_count": 6,
    "suggestions_count": 45,
    "alternative_names": [],
    "metacritic_url": "",
    "parents_count": 0,
    "additions_count": 0,
    "game_series_count": 13,
    "user_game": null,
    "reviews_count": 7,
    "saturated_color": "0f0f0f",
    "dominant_color": "0f0f0f",
    "parent_platforms": [
      {
        "platform": {
          "id": 1,
          "name": "PC",
          "slug": "pc"
        }
      },
      {
        "platform": {
          "id": 3,
          "name": "Xbox",
          "slug": "xbox"
        }
      }
    ],
    "platforms": [
      {
        "platform": {
          "id": 4,
          "name": "PC",
          "slug": "pc",
          "image": null,
          "year_end": null,
          "year_start": null,
          "games_count": 547584,
          "image_background": "https://media.rawg.io/media/games/736/73619bd336c894d6941d926bfd563946.jpg"
        },
        "released_at": null,
        "requirements": {}
      },
      {
        "platform": {
          "id": 186,
          "name": "Xbox Series S/X",
          "slug": "xbox-series-x",
          "image": null,
          "year_end": null,
          "year_start": 2020,
          "games_count": 1077,
          "image_background": "https://media.rawg.io/media/games/6cc/6cc23249972a427f697a3d10eb57a820.jpg"
        },
        "released_at": null,
        "requirements": {}
      }
    ],
    "stores": [],
    "developers": [
      {
        "id": 4207,
        "name": "Bethesda Game Studios",
        "slug": "bethesda-game-studios",
        "games_count": 41,
        "image_background": "https://media.rawg.io/media/screenshots/5a6/5a63022f15130f18ac58621070e375cd.jpg"
      }
    ],
    "genres": [
      {
        "id": 4,
        "name": "Action",
        "slug": "action",
        "games_count": 186754,
        "image_background": "https://media.rawg.io/media/games/942/9424d6bb763dc38d9378b488603c87fa.jpg"
      },
      {
        "id": 5,
        "name": "RPG",
        "slug": "role-playing-games-rpg",
        "games_count": 59443,
        "image_background": "https://media.rawg.io/media/games/713/713269608dc8f2f40f5a670a14b2de94.jpg"
      }
    ],
    "tags": [
      {
        "id": 31,
        "name": "Singleplayer",
        "slug": "singleplayer",
        "language": "eng",
        "games_count": 238777,
        "image_background": "https://media.rawg.io/media/games/8cc/8cce7c0e99dcc43d66c8efd42f9d03e3.jpg"
      },
      {
        "id": 13,
        "name": "Atmospheric",
        "slug": "atmospheric",
        "language": "eng",
        "games_count": 36784,
        "image_background": "https://media.rawg.io/media/games/20a/20aa03a10cda45239fe22d035c0ebe64.jpg"
      },
      {
        "id": 24,
        "name": "RPG",
        "slug": "rpg",
        "language": "eng",
        "games_count": 24180,
        "image_background": "https://media.rawg.io/media/games/fc1/fc1307a2774506b5bd65d7e8424664a7.jpg"
      },
      {
        "id": 36,
        "name": "Open World",
        "slug": "open-world",
        "language": "eng",
        "games_count": 8508,
        "image_background": "https://media.rawg.io/media/games/d82/d82990b9c67ba0d2d09d4e6fa88885a7.jpg"
      },
      {
        "id": 8,
        "name": "First-Person",
        "slug": "first-person",
        "language": "eng",
        "games_count": 34786,
        "image_background": "https://media.rawg.io/media/games/9dd/9ddabb34840ea9227556670606cf8ea3.jpg"
      },
      {
        "id": 64,
        "name": "Fantasy",
        "slug": "fantasy",
        "language": "eng",
        "games_count": 30681,
        "image_background": "https://media.rawg.io/media/games/04a/04a7e7e185fb51493bdcbe1693a8b3dc.jpg"
      },
      {
        "id": 6,
        "name": "Exploration",
        "slug": "exploration",
        "language": "eng",
        "games_count": 26446,
        "image_background": "https://media.rawg.io/media/games/4cf/4cfc6b7f1850590a4634b08bfab308ab.jpg"
      },
      {
        "id": 69,
        "name": "Action-Adventure",
        "slug": "action-adventure",
        "language": "eng",
        "games_count": 19060,
        "image_background": "https://media.rawg.io/media/games/af7/af7a831001c5c32c46e950cc883b8cb7.jpg"
      },
      {
        "id": 478,
        "name": "3rd-Person Perspective",
        "slug": "3rd-person-perspective",
        "language": "eng",
        "games_count": 87,
        "image_background": "https://media.rawg.io/media/games/909/909974d1c7863c2027241e265fe7011f.jpg"
      },
      {
        "id": 215,
        "name": "Dragons",
        "slug": "dragons",
        "language": "eng",
        "games_count": 2759,
        "image_background": "https://media.rawg.io/media/screenshots/755/7557715b92e3db2914e73c4fccfa7fdc.jpg"
      },
      {
        "id": 324,
        "name": "Experience",
        "slug": "experience",
        "language": "eng",
        "games_count": 294,
        "image_background": "https://media.rawg.io/media/screenshots/291/29135ecd06cd54c4f13a8bcddbba8fba.jpg"
      }
    ],
    "publishers": [
      {
        "id": 339,
        "name": "Bethesda Softworks",
        "slug": "bethesda-softworks",
        "games_count": 184,
        "image_background": "https://media.rawg.io/media/games/587/587588c64afbff80e6f444eb2e46f9da.jpg"
      }
    ],
    "esrb_rating": null,
    "clip": null,
    "description_raw": "Currently in pre-production at Bethesda Game Studios, the acclaimed developers of Skyrim and Fallout 4. The highly-anticipated next chapter in the iconic The Elder Scrolls series."
  },
  {
    "id": 974923,
    "slug": "winter-memories-2",
    "name": "Winter Memories",
    "name_original": "Winter Memories",
    "description": "After the unforgettable summer memories you’ve made half a year ago, Yui, Rio, and Miyuki are back. With the change of seasons and the cold falling snow, a new page to your story is about to begin. Revisit the peaceful, seaside town, and spend time catching up with your family and friends.What new memories will you make this winter?A Relaxing, Adventure RPGExplore the Beautiful, Seaside TownManage How You Spend Your TIme",
    "metacritic": null,
    "metacritic_platforms": [],
    "released": "2024-01-05",
    "tba": false,
    "updated": "2025-01-04T16:30:52",
    "background_image": "https://media.rawg.io/media/screenshots/326/326267a294202a9d93e55879a6f61d48.jpg",
    "background_image_additional": "https://media.rawg.io/media/screenshots/22b/22bad148e80732be27db151f30703e56.jpg",
    "website": "",
    "rating": 4.83,
    "rating_top": 5,
    "ratings": [
      {
        "id": 5,
        "title": "exceptional",
        "count": 5,
        "percent": 83.33
      },
      {
        "id": 4,
        "title": "recommended",
        "count": 1,
        "percent": 16.67
      }
    ],
    "reactions": null,
    "added": 33,
    "added_by_status": {
      "yet": 2,
      "owned": 18,
      "beaten": 8,
      "toplay": 4,
      "playing": 1
    },
    "playtime": 6,
    "screenshots_count": 5,
    "movies_count": 0,
    "creators_count": 0,
    "achievements_count": 0,
    "parent_achievements_count": 0,
    "reddit_url": "",
    "reddit_name": "",
    "reddit_description": "",
    "reddit_logo": "",
    "reddit_count": 0,
    "twitch_count": 0,
    "youtube_count": 0,
    "reviews_text_count": 0,
    "ratings_count": 6,
    "suggestions_count": 177,
    "alternative_names": [],
    "metacritic_url": "",
    "parents_count": 0,
    "additions_count": 0,
    "game_series_count": 0,
    "user_game": null,
    "reviews_count": 6,
    "saturated_color": "0f0f0f",
    "dominant_color": "0f0f0f",
    "parent_platforms": [
      {
        "platform": {
          "id": 1,
          "name": "PC",
          "slug": "pc"
        }
      }
    ],
    "platforms": [
      {
        "platform": {
          "id": 4,
          "name": "PC",
          "slug": "pc",
          "image": null,
          "year_end": null,
          "year_start": null,
          "games_count": 547583,
          "image_background": "https://media.rawg.io/media/games/fc1/fc1307a2774506b5bd65d7e8424664a7.jpg"
        },
        "released_at": "2024-01-05",
        "requirements": {
          "minimum": "Minimum:\nOS *: Windows® 7/8/8.1/10/11\nProcessor: Intel Core2 Duo or better\nMemory: 4 GB RAM\nGraphics: DirectX 9/OpenGL 4.1 capable GPU\nDirectX: Version 9.0\nStorage: 2 GB available space\nAdditional Notes: 1280x768 or better Display.  Lag may occur from loading menus or maps.  Turn off other programs before running the game.",
          "recommended": "Recommended:\nOS *: Windows® 7/8/8.1/10/11\nProcessor: 2+ GHz Processor\nMemory: 4 GB RAM\nGraphics: OpenGL ES 2.0 hardware driver support required for WebGL acceleration. (AMD Catalyst 10.9, nVidia 358.50)\nStorage: 4 GB available space\nAdditional Notes: 1280x768 or better Display.  Lag may occur from loading menus or maps.  Turn off other programs before running the game."
        }
      }
    ],
    "stores": [
      {
        "id": 975162,
        "url": "",
        "store": {
          "id": 5,
          "name": "GOG",
          "slug": "gog",
          "domain": "gog.com",
          "games_count": 6725,
          "image_background": "https://media.rawg.io/media/games/f46/f466571d536f2e3ea9e815ad17177501.jpg"
        }
      },
      {
        "id": 975128,
        "url": "",
        "store": {
          "id": 1,
          "name": "Steam",
          "slug": "steam",
          "domain": "store.steampowered.com",
          "games_count": 110568,
          "image_background": "https://media.rawg.io/media/games/942/9424d6bb763dc38d9378b488603c87fa.jpg"
        }
      }
    ],
    "developers": [
      {
        "id": 221383,
        "name": "Dojin Otome",
        "slug": "dojin-otome",
        "games_count": 2,
        "image_background": "https://media.rawg.io/media/screenshots/326/326267a294202a9d93e55879a6f61d48.jpg"
      }
    ],
    "genres": [
      {
        "id": 3,
        "name": "Adventure",
        "slug": "adventure",
        "games_count": 146620,
        "image_background": "https://media.rawg.io/media/games/c50/c5085506fe4b5e20fc7aa5ace842c20b.jpg"
      },
      {
        "id": 5,
        "name": "RPG",
        "slug": "role-playing-games-rpg",
        "games_count": 59442,
        "image_background": "https://media.rawg.io/media/games/1f4/1f47a270b8f241e4676b14d39ec620f7.jpg"
      },
      {
        "id": 14,
        "name": "Simulation",
        "slug": "simulation",
        "games_count": 73580,
        "image_background": "https://media.rawg.io/media/screenshots/f2f/f2f3c93d6153da7aee590f3ab8ccd803.jpg"
      },
      {
        "id": 40,
        "name": "Casual",
        "slug": "casual",
        "games_count": 61500,
        "image_background": "https://media.rawg.io/media/screenshots/6fe/6fe228662a253cd929cc78a103541ee0.jpg"
      }
    ],
    "tags": [
      {
        "id": 31,
        "name": "Singleplayer",
        "slug": "singleplayer",
        "language": "eng",
        "games_count": 238777,
        "image_background": "https://media.rawg.io/media/games/8cc/8cce7c0e99dcc43d66c8efd42f9d03e3.jpg"
      },
      {
        "id": 40849,
        "name": "Steam Cloud",
        "slug": "steam-cloud",
        "language": "eng",
        "games_count": 21933,
        "image_background": "https://media.rawg.io/media/games/be0/be01c3d7d8795a45615da139322ca080.jpg"
      },
      {
        "id": 24,
        "name": "RPG",
        "slug": "rpg",
        "language": "eng",
        "games_count": 24180,
        "image_background": "https://media.rawg.io/media/games/fc1/fc1307a2774506b5bd65d7e8424664a7.jpg"
      },
      {
        "id": 30,
        "name": "FPS",
        "slug": "fps",
        "language": "eng",
        "games_count": 14224,
        "image_background": "https://media.rawg.io/media/games/d58/d588947d4286e7b5e0e12e1bea7d9844.jpg"
      },
      {
        "id": 122,
        "name": "Pixel Graphics",
        "slug": "pixel-graphics",
        "language": "eng",
        "games_count": 96691,
        "image_background": "https://media.rawg.io/media/games/9fa/9fa63622543e5d4f6d99aa9d73b043de.jpg"
      },
      {
        "id": 134,
        "name": "Anime",
        "slug": "anime",
        "language": "eng",
        "games_count": 15394,
        "image_background": "https://media.rawg.io/media/games/c40/c40f9f0a3d1b4601a7a44d230c95f126.jpg"
      },
      {
        "id": 44,
        "name": "Nudity",
        "slug": "nudity",
        "language": "eng",
        "games_count": 7753,
        "image_background": "https://media.rawg.io/media/games/a0e/a0ef08621301a1eab5e04fa5c96978fa.jpeg"
      },
      {
        "id": 88,
        "name": "Cute",
        "slug": "cute",
        "language": "eng",
        "games_count": 36919,
        "image_background": "https://media.rawg.io/media/games/c40/c40f9f0a3d1b4601a7a44d230c95f126.jpg"
      },
      {
        "id": 192,
        "name": "Mature",
        "slug": "mature",
        "language": "eng",
        "games_count": 4033,
        "image_background": "https://media.rawg.io/media/games/13a/13a528ac9cf48bbb6be5d35fe029336d.jpg"
      },
      {
        "id": 50,
        "name": "Sexual Content",
        "slug": "sexual-content",
        "language": "eng",
        "games_count": 7586,
        "image_background": "https://media.rawg.io/media/games/370/3703c683968a54f09630dcf03366ea35.jpg"
      },
      {
        "id": 90,
        "name": "Visual Novel",
        "slug": "visual-novel",
        "language": "eng",
        "games_count": 8524,
        "image_background": "https://media.rawg.io/media/games/c60/c60be8ddf91ede65c65b13eff2e06c37.jpg"
      },
      {
        "id": 233,
        "name": "JRPG",
        "slug": "jrpg",
        "language": "eng",
        "games_count": 4828,
        "image_background": "https://media.rawg.io/media/games/3ea/3ea0e57ede873970c0f1130e30d88749.jpg"
      },
      {
        "id": 312,
        "name": "NSFW",
        "slug": "nsfw",
        "language": "eng",
        "games_count": 4169,
        "image_background": "https://media.rawg.io/media/games/85f/85f9c6504b3a43298216691619cc37fe.jpg"
      },
      {
        "id": 786,
        "name": "hentai",
        "slug": "hentai",
        "language": "eng",
        "games_count": 3235,
        "image_background": "https://media.rawg.io/media/screenshots/c1f/c1f104c610cc78e05f6c0766edf81903.jpg"
      },
      {
        "id": 58128,
        "name": "Хентай",
        "slug": "khentai",
        "language": "eng",
        "games_count": 2847,
        "image_background": "https://media.rawg.io/media/screenshots/907/90738715f735af95811e292ede73ed44.jpg"
      }
    ],
    "publishers": [
      {
        "id": 21329,
        "name": "Kagura Games",
        "slug": "kagura-games",
        "games_count": 179,
        "image_background": "https://media.rawg.io/media/screenshots/723/7239aacdf3bf58adee2e8cb4c7f52f35.jpg"
      }
    ],
    "esrb_rating": null,
    "clip": null,
    "description_raw": "Latest Releasehttps://store.steampowered.com/app/2687990/The_Black_Guards_of_Odom__Desert_Town_Prison/\nhttps://store.steampowered.com/app/1551550/Philana_and_the_Elixir_of_Life/\nhttps://store.steampowered.com/app/2420620/Demon_Slayer_Shion/\nUpcoming Gameshttps://store.steampowered.com/app/2429890/Incubus_Quest/\nhttps://store.steampowered.com/app/2582660/And_the_Hero_Was_Never_Seen_Again/\nAbout the Game\nAfter the unforgettable summer memories you’ve made half a year ago, Yui, Rio, and Miyuki are back. With the change of seasons and the cold falling snow, a new page to your story is about to begin.\nRevisit the peaceful, seaside town, and spend time catching up with your family and friends.\nWhat new memories will you make this winter?\nA Relaxing, Adventure RPG\nExplore the Beautiful, Seaside Town\nManage How You Spend Your TIme"
  },
  {
    "id": 964507,
    "slug": "geometry-dash-razorleaf",
    "name": "Geometry Dash RazorLeaf",
    "name_original": "Geometry Dash RazorLeaf",
    "description": "Geometry Dash RazorLeaf is a casual arcade game. It was originally released in 2023. Most rawgers rated the game as \"Exceptional\". Geometry Dash RazorLeaf is available on Android and PC.",
    "metacritic": null,
    "metacritic_platforms": [],
    "released": "2023-07-19",
    "tba": false,
    "updated": "2025-01-30T12:29:24",
    "background_image": "https://media.rawg.io/media/screenshots/8ad/8ad83b99a7ea2116a72688ba26644b3f.jpg",
    "background_image_additional": null,
    "website": "",
    "rating": 4.83,
    "rating_top": 5,
    "ratings": [
      {
        "id": 5,
        "title": "exceptional",
        "count": 5,
        "percent": 83.33
      },
      {
        "id": 4,
        "title": "recommended",
        "count": 1,
        "percent": 16.67
      }
    ],
    "reactions": {
      "5": 1
    },
    "added": 23,
    "added_by_status": {
      "yet": 2,
      "owned": 10,
      "beaten": 1,
      "toplay": 5,
      "playing": 5
    },
    "playtime": 0,
    "screenshots_count": 1,
    "movies_count": 0,
    "creators_count": 0,
    "achievements_count": 0,
    "parent_achievements_count": 0,
    "reddit_url": "",
    "reddit_name": "",
    "reddit_description": "",
    "reddit_logo": "",
    "reddit_count": 0,
    "twitch_count": 0,
    "youtube_count": 0,
    "reviews_text_count": 1,
    "ratings_count": 5,
    "suggestions_count": 27,
    "alternative_names": [],
    "metacritic_url": "",
    "parents_count": 0,
    "additions_count": 0,
    "game_series_count": 0,
    "user_game": null,
    "reviews_count": 6,
    "saturated_color": "0f0f0f",
    "dominant_color": "0f0f0f",
    "parent_platforms": [
      {
        "platform": {
          "id": 1,
          "name": "PC",
          "slug": "pc"
        }
      },
      {
        "platform": {
          "id": 8,
          "name": "Android",
          "slug": "android"
        }
      }
    ],
    "platforms": [
      {
        "platform": {
          "id": 21,
          "name": "Android",
          "slug": "android",
          "image": null,
          "year_end": null,
          "year_start": null,
          "games_count": 52428,
          "image_background": "https://media.rawg.io/media/games/a91/a911f0a91991469e398fa70091507a5b.jpg"
        },
        "released_at": "2023-07-19",
        "requirements": {}
      },
      {
        "platform": {
          "id": 4,
          "name": "PC",
          "slug": "pc",
          "image": null,
          "year_end": null,
          "year_start": null,
          "games_count": 547583,
          "image_background": "https://media.rawg.io/media/games/fc1/fc1307a2774506b5bd65d7e8424664a7.jpg"
        },
        "released_at": "2023-07-19",
        "requirements": {}
      }
    ],
    "stores": [],
    "developers": [],
    "genres": [
      {
        "id": 11,
        "name": "Arcade",
        "slug": "arcade",
        "games_count": 22659,
        "image_background": "https://media.rawg.io/media/games/cfe/cfe114c081281960bd79ace5209c0a4a.jpg"
      },
      {
        "id": 40,
        "name": "Casual",
        "slug": "casual",
        "games_count": 61500,
        "image_background": "https://media.rawg.io/media/screenshots/6fe/6fe228662a253cd929cc78a103541ee0.jpg"
      },
      {
        "id": 51,
        "name": "Indie",
        "slug": "indie",
        "games_count": 77227,
        "image_background": "https://media.rawg.io/media/games/d0f/d0f91fe1d92332147e5db74e207cfc7a.jpg"
      }
    ],
    "tags": [],
    "publishers": [],
    "esrb_rating": null,
    "clip": null,
    "description_raw": ""
  },
  {
    "id": 932677,
    "slug": "octopath-traveler-ii",
    "name": "OCTOPATH TRAVELER II",
    "name_original": "OCTOPATH TRAVELER II",
    "description": "The story takes place in Solistia, a land comprising an eastern and western continent divided by the sea. It is a bustling era, wherein large vessels navigate busy sea routes and the power of steam gives birth to new technologies.Some people thrill to glamorous stars of the stage and industry, while others are brought to tears by war, plague, and poverty.In this faraway realm, eight travelers hailing from different regions venture forth for their own reasons. Step into their shoes and explore the land as you see fit, using their unique talents to aid you along your journey. Embark on an adventure all your own.KEY FEATURESBegin your adventure as one of eight new travelers, each with their own origins, motivations, and unique skills.The series’ HD-2D graphics, a fusion of retro pixel art and 3DCG, have reached even greater heights.The story takes place in Solistia, where diverse cultures thrive from east to west and the industries of the new era flourish. You can sail the seas and explore every corner of a world that changes from day to night.Each traveler has a unique set of Path Actions they can use to battle townspeople, obtain items, take others along in their travels, and more. Where will you go? What will you do? Every path is yours to take.Familiar mechanics from the original game have been preserved, like the freedom to develop your travelers’ jobs and skills, as well as the Break and Boost system that made battles so exhilarating. New mechanics have also been added.",
    "metacritic": null,
    "metacritic_platforms": [],
    "released": null,
    "tba": false,
    "updated": "2025-02-28T15:45:24",
    "background_image": "https://media.rawg.io/media/screenshots/7c0/7c015e0ab17a4255a9dd8452eeb96e50.jpg",
    "background_image_additional": "https://media.rawg.io/media/screenshots/f73/f7324e0e2eb93452a3d1f6631eb9ccb1.jpg",
    "website": "",
    "rating": 4.71,
    "rating_top": 5,
    "ratings": [
      {
        "id": 5,
        "title": "exceptional",
        "count": 5,
        "percent": 71.43
      },
      {
        "id": 4,
        "title": "recommended",
        "count": 2,
        "percent": 28.57
      }
    ],
    "reactions": null,
    "added": 80,
    "added_by_status": {
      "yet": 5,
      "owned": 69,
      "beaten": 1,
      "toplay": 3,
      "dropped": 1,
      "playing": 1
    },
    "playtime": 10,
    "screenshots_count": 6,
    "movies_count": 0,
    "creators_count": 0,
    "achievements_count": 24,
    "parent_achievements_count": 24,
    "reddit_url": "",
    "reddit_name": "",
    "reddit_description": "",
    "reddit_logo": "",
    "reddit_count": 0,
    "twitch_count": 0,
    "youtube_count": 0,
    "reviews_text_count": 0,
    "ratings_count": 7,
    "suggestions_count": 399,
    "alternative_names": [],
    "metacritic_url": "",
    "parents_count": 0,
    "additions_count": 0,
    "game_series_count": 0,
    "user_game": null,
    "reviews_count": 7,
    "saturated_color": "0f0f0f",
    "dominant_color": "0f0f0f",
    "parent_platforms": [
      {
        "platform": {
          "id": 1,
          "name": "PC",
          "slug": "pc"
        }
      }
    ],
    "platforms": [
      {
        "platform": {
          "id": 4,
          "name": "PC",
          "slug": "pc",
          "image": null,
          "year_end": null,
          "year_start": null,
          "games_count": 547965,
          "image_background": "https://media.rawg.io/media/games/fc1/fc1307a2774506b5bd65d7e8424664a7.jpg"
        },
        "released_at": null,
        "requirements": {
          "minimum": "Minimum:\nOS: Windows® 10 / 11 64-bit\nProcessor: AMD Ryzen™ 3 1200 / Intel® Core™ i3-6100\nMemory: 8 GB RAM\nGraphics: AMD Radeon™ RX 460 / NVIDIA® GeForce® GTX 750\nDirectX: Version 12\nStorage: 10 GB available space\nAdditional Notes: 60 FPS @ 1280x720, Preset &quot;Low&quot;, 2GB VRAM required",
          "recommended": "Recommended:\nOS: Windows® 10 / 11 64-bit\nProcessor: AMD Ryzen™ 3 1200 / Intel® Core™ i5-6400\nMemory: 8 GB RAM\nGraphics: AMD Radeon™ RX 470 / Intel® Arc™ A750 / NVIDIA® GeForce® GTX 1060 6GB VRAM\nDirectX: Version 12\nStorage: 10 GB available space\nAdditional Notes: 60 FPS @ 1920x1080, Preset &quot;Highest&quot;, Systen RAM 16GB required when running on Intel GPU"
        }
      }
    ],
    "stores": [
      {
        "id": 931099,
        "url": "",
        "store": {
          "id": 1,
          "name": "Steam",
          "slug": "steam",
          "domain": "store.steampowered.com",
          "games_count": 110950,
          "image_background": "https://media.rawg.io/media/games/120/1201a40e4364557b124392ee50317b99.jpg"
        }
      }
    ],
    "developers": [
      {
        "id": 4132,
        "name": "Square Enix",
        "slug": "square-enix",
        "games_count": 368,
        "image_background": "https://media.rawg.io/media/games/214/2140885d34e3a3398b45036e5d870971.jpg"
      },
      {
        "id": 10964,
        "name": "Acquire",
        "slug": "acquire",
        "games_count": 42,
        "image_background": "https://media.rawg.io/media/games/87e/87e6d38aaa58ef00280626d876115e42.jpg"
      }
    ],
    "genres": [
      {
        "id": 5,
        "name": "RPG",
        "slug": "role-playing-games-rpg",
        "games_count": 59505,
        "image_background": "https://media.rawg.io/media/games/a6c/a6ccd34125c594abf1a9c9821b9a715d.jpg"
      }
    ],
    "tags": [
      {
        "id": 31,
        "name": "Singleplayer",
        "slug": "singleplayer",
        "language": "eng",
        "games_count": 239144,
        "image_background": "https://media.rawg.io/media/games/73e/73eecb8909e0c39fb246f457b5d6cbbe.jpg"
      },
      {
        "id": 40847,
        "name": "Steam Achievements",
        "slug": "steam-achievements",
        "language": "eng",
        "games_count": 45430,
        "image_background": "https://media.rawg.io/media/games/20a/20aa03a10cda45239fe22d035c0ebe64.jpg"
      },
      {
        "id": 40836,
        "name": "Full controller support",
        "slug": "full-controller-support",
        "language": "eng",
        "games_count": 21419,
        "image_background": "https://media.rawg.io/media/games/4be/4be6a6ad0364751a96229c56bf69be59.jpg"
      },
      {
        "id": 40849,
        "name": "Steam Cloud",
        "slug": "steam-cloud",
        "language": "eng",
        "games_count": 22047,
        "image_background": "https://media.rawg.io/media/games/e6d/e6de699bd788497f4b52e2f41f9698f2.jpg"
      },
      {
        "id": 13,
        "name": "Atmospheric",
        "slug": "atmospheric",
        "language": "eng",
        "games_count": 36877,
        "image_background": "https://media.rawg.io/media/games/737/737ea5662211d2e0bbd6f5989189e4f1.jpg"
      },
      {
        "id": 24,
        "name": "RPG",
        "slug": "rpg",
        "language": "eng",
        "games_count": 24245,
        "image_background": "https://media.rawg.io/media/games/618/618c2031a07bbff6b4f611f10b6bcdbc.jpg"
      },
      {
        "id": 118,
        "name": "Story Rich",
        "slug": "story-rich",
        "language": "eng",
        "games_count": 24813,
        "image_background": "https://media.rawg.io/media/games/6cd/6cd653e0aaef5ff8bbd295bf4bcb12eb.jpg"
      },
      {
        "id": 36,
        "name": "Open World",
        "slug": "open-world",
        "language": "eng",
        "games_count": 8539,
        "image_background": "https://media.rawg.io/media/games/e6d/e6de699bd788497f4b52e2f41f9698f2.jpg"
      },
      {
        "id": 64,
        "name": "Fantasy",
        "slug": "fantasy",
        "language": "eng",
        "games_count": 30755,
        "image_background": "https://media.rawg.io/media/games/af7/af7a831001c5c32c46e950cc883b8cb7.jpg"
      },
      {
        "id": 122,
        "name": "Pixel Graphics",
        "slug": "pixel-graphics",
        "language": "eng",
        "games_count": 96757,
        "image_background": "https://media.rawg.io/media/games/003/0031c0067559d41df19cf98ad87e02aa.jpg"
      },
      {
        "id": 134,
        "name": "Anime",
        "slug": "anime",
        "language": "eng",
        "games_count": 15437,
        "image_background": "https://media.rawg.io/media/games/bee/bee483efadcf9d7e657e52184316a34e.jpg"
      },
      {
        "id": 102,
        "name": "Turn-Based",
        "slug": "turn-based",
        "language": "eng",
        "games_count": 5479,
        "image_background": "https://media.rawg.io/media/games/fd9/fd92f105dcd6491bc5d61135033d1f19.jpg"
      },
      {
        "id": 88,
        "name": "Cute",
        "slug": "cute",
        "language": "eng",
        "games_count": 37010,
        "image_background": "https://media.rawg.io/media/games/fae/faebf3c8cbf30db3f46bfbecf6ada3d6.jpg"
      },
      {
        "id": 145,
        "name": "Choices Matter",
        "slug": "choices-matter",
        "language": "eng",
        "games_count": 7077,
        "image_background": "https://media.rawg.io/media/games/704/704f831d2d132e9614931f1c4eab9e86.jpg"
      },
      {
        "id": 82,
        "name": "Magic",
        "slug": "magic",
        "language": "eng",
        "games_count": 10548,
        "image_background": "https://media.rawg.io/media/games/d1a/d1a2e99ade53494c6330a0ed945fe823.jpg"
      },
      {
        "id": 40937,
        "name": "Steam Trading Cards",
        "slug": "steam-trading-cards-2",
        "language": "eng",
        "games_count": 750,
        "image_background": "https://media.rawg.io/media/games/260/26023c855f1769a93411d6a7ea084632.jpeg"
      },
      {
        "id": 233,
        "name": "JRPG",
        "slug": "jrpg",
        "language": "eng",
        "games_count": 4835,
        "image_background": "https://media.rawg.io/media/games/b2c/b2c9c6115114c8f7d461b5430e8a7d4a.jpg"
      },
      {
        "id": 116,
        "name": "2.5D",
        "slug": "25d",
        "language": "eng",
        "games_count": 2540,
        "image_background": "https://media.rawg.io/media/games/075/0753492cda7ee3c9bd4a3ca673fd0c8c.jpg"
      },
      {
        "id": 175,
        "name": "Turn-Based Combat",
        "slug": "turn-based-combat",
        "language": "eng",
        "games_count": 5744,
        "image_background": "https://media.rawg.io/media/games/75c/75c086892cbf0aed952293f440a935a4.jpg"
      },
      {
        "id": 572,
        "name": "Emotional",
        "slug": "emotional",
        "language": "eng",
        "games_count": 3792,
        "image_background": "https://media.rawg.io/media/games/7ad/7adc6352280fe0e6626902e444e22195.jpg"
      },
      {
        "id": 206,
        "name": "Party-Based RPG",
        "slug": "party-based-rpg",
        "language": "eng",
        "games_count": 1358,
        "image_background": "https://media.rawg.io/media/games/d89/d89bd0cf4fcdc10820892980cbba0f49.jpg"
      }
    ],
    "publishers": [
      {
        "id": 308,
        "name": "Square Enix",
        "slug": "square-enix",
        "games_count": 601,
        "image_background": "https://media.rawg.io/media/games/59a/59a3ebcba3d08c51532c6ca877aff256.jpg"
      }
    ],
    "esrb_rating": null,
    "clip": null,
    "description_raw": "OCTOPATH TRAVELER II Prologue Demo\nA free demo is now available! You can choose any of the eight protagonists, play for three hours, and carry over your saved game data to the full game. Travel beyond starting areas is restricted, but you can explore those corners of Solistia to your heart's content.\nAbout the GameThe story takes place in Solistia, a land comprising an eastern and western continent divided by the sea.\nIt is a bustling era, wherein large vessels navigate busy sea routes and the power of steam gives birth to new technologies.\nSome people thrill to glamorous stars of the stage and industry, while others are brought to tears by war, plague, and poverty.\nIn this faraway realm, eight travelers hailing from different regions venture forth for their own reasons. Step into their shoes and explore the land as you see fit, using their unique talents to aid you along your journey.\nEmbark on an adventure all your own.KEY FEATURESBegin your adventure as one of eight new travelers, each with their own origins, motivations, and unique skills.\nThe series’ HD-2D graphics, a fusion of retro pixel art and 3DCG, have reached even greater heights.\nThe story takes place in Solistia, where diverse cultures thrive from east to west and the industries of the new era flourish. You can sail the seas and explore every corner of a world that changes from day to night.\nEach traveler has a unique set of Path Actions they can use to battle townspeople, obtain items, take others along in their travels, and more. Where will you go? What will you do? Every path is yours to take.\nFamiliar mechanics from the original game have been preserved, like the freedom to develop your travelers’ jobs and skills, as well as the Break and Boost system that made battles so exhilarating. New mechanics have also been added."
  }
]